{"totalCorrect":16,"totalWrong":35,"repliesList":[{"corrects":1,"wrongs":2,"repliesRecord":["correct","correct","incorrect"]},{"corrects":2,"wrongs":1,"repliesRecord":["correct","incorrect","incorrect"]},{"corrects":1,"wrongs":2,"repliesRecord":["correct","incorrect","correct"]},{"corrects":0,"wrongs":3,"repliesRecord":["correct","correct","correct"]},{"corrects":1,"wrongs":2,"repliesRecord":["correct","correct","incorrect"]},{"corrects":1,"wrongs":2,"repliesRecord":["correct","correct","incorrect"]},{"corrects":1,"wrongs":2,"repliesRecord":["correct","correct","incorrect"]},{"corrects":4,"wrongs":6,"repliesRecord":["incorrect","correct","incorrect","correct","correct","incorrect","correct","incorrect","correct","correct"]},{"corrects":1,"wrongs":9,"repliesRecord":["correct","correct","incorrect","correct","correct","correct","correct","correct","correct","correct"]},{"corrects":4,"wrongs":6,"repliesRecord":["incorrect","correct","incorrect","incorrect","correct","incorrect","correct","incorrect","incorrect","correct"]}]}